odoo/addons/l10n_es_atc_mod417/README.rst
odoo/addons/l10n_es_atc_mod417/__init__.py
odoo/addons/l10n_es_atc_mod417/__manifest__.py
odoo/addons/l10n_es_atc_mod417/data/l10n.es.aeat.map.tax.csv
odoo/addons/l10n_es_atc_mod417/data/l10n.es.aeat.map.tax.line.account.csv
odoo/addons/l10n_es_atc_mod417/data/l10n.es.aeat.map.tax.line.csv
odoo/addons/l10n_es_atc_mod417/data/l10n.es.aeat.map.tax.line.tax.csv
odoo/addons/l10n_es_atc_mod417/i18n/es.po
odoo/addons/l10n_es_atc_mod417/i18n/l10n_es_atc_mod417.pot
odoo/addons/l10n_es_atc_mod417/migrations/17.0.1.2.0/pre-migration.py
odoo/addons/l10n_es_atc_mod417/models/__init__.py
odoo/addons/l10n_es_atc_mod417/models/mod417.py
odoo/addons/l10n_es_atc_mod417/readme/CONTRIBUTORS.md
odoo/addons/l10n_es_atc_mod417/readme/DESCRIPTION.md
odoo/addons/l10n_es_atc_mod417/readme/INSTALL.md
odoo/addons/l10n_es_atc_mod417/readme/ROADMAP.md
odoo/addons/l10n_es_atc_mod417/readme/USAGE.md
odoo/addons/l10n_es_atc_mod417/reports/Presentacion-417-XMLSchema.xsd
odoo/addons/l10n_es_atc_mod417/reports/mod417_report.xml
odoo/addons/l10n_es_atc_mod417/security/ir.model.access.csv
odoo/addons/l10n_es_atc_mod417/security/l10n_es_atc_mod417_security.xml
odoo/addons/l10n_es_atc_mod417/static/description/icon.png
odoo/addons/l10n_es_atc_mod417/static/description/index.html
odoo/addons/l10n_es_atc_mod417/static/src/pdf/caratula_sobre_420.pdf
odoo/addons/l10n_es_atc_mod417/tests/__init__.py
odoo/addons/l10n_es_atc_mod417/tests/test_l10n_es_atc_mod417.py
odoo/addons/l10n_es_atc_mod417/views/mod417_view.xml
odoo_addon_l10n_es_atc_mod417-17.0.1.2.1.dist-info/METADATA
odoo_addon_l10n_es_atc_mod417-17.0.1.2.1.dist-info/WHEEL
odoo_addon_l10n_es_atc_mod417-17.0.1.2.1.dist-info/top_level.txt
odoo_addon_l10n_es_atc_mod417-17.0.1.2.1.dist-info/RECORD
